cauliflow/__init__.py
cauliflow/blackboard.py
cauliflow/cli.py
cauliflow/context.py
cauliflow/filters.py
cauliflow/flow.py
cauliflow/flowdata.py
cauliflow/loader.py
cauliflow/logging.py
cauliflow/macros.py
cauliflow/node.py
cauliflow/plugin_manager.py
cauliflow/py.typed
cauliflow/variable.py
cauliflow/plugins/__init__.py
cauliflow/plugins/buffer.py
cauliflow/plugins/ca.py
cauliflow/plugins/csv.py
cauliflow/plugins/file.py
cauliflow/plugins/flowcontrol.py
cauliflow/plugins/http.py
cauliflow/plugins/itemloop.py
cauliflow/plugins/message.py
cauliflow/plugins/root.py
cauliflow/plugins/stdio.py
cauliflow/plugins/timer.py
cauliflow/plugins/transforms.py
cauliflow/plugins/zabbix.py
cauliflow-0.2.0.dist-info/METADATA
cauliflow-0.2.0.dist-info/WHEEL
cauliflow-0.2.0.dist-info/entry_points.txt
cauliflow-0.2.0.dist-info/licenses/LICENSE
cauliflow-0.2.0.dist-info/RECORD
